<annotation verified="yes">
    <folder>Annotation</folder>
    <filename>3.jpg</filename>
    <path>1stpractice-PascalVOC-export/Annotations/3.jpg</path>
    <source>
        <database>Unknown</database>
    </source>
    <size>
        <width>300</width>
        <height>168</height>
        <depth>3</depth>
    </size>
    <segmented>0</segmented>
    <object>
    <name>box2</name>
    <pose>Unspecified</pose>
    <truncated>0</truncated>
    <difficult>0</difficult>
    <bndbox>
        <xmin>50.16835016835017</xmin>
        <ymin>65.81437875751503</ymin>
        <xmax>154.54545454545456</xmax>
        <ymax>146.61598196392785</ymax>
    </bndbox>
</object>
</annotation>
